setup.py
opal_wardround.egg-info/PKG-INFO
opal_wardround.egg-info/SOURCES.txt
opal_wardround.egg-info/dependency_links.txt
opal_wardround.egg-info/top_level.txt
wardround/__init__.py
wardround/api.py
wardround/models.py
wardround/urls.py
wardround/views.py
wardround/wardrounds.py